Workbook

Sheet Página inicial
A1: 🚀 GABINETE DE GOVERNANÇA - OVERVIEW EXECUTIVO DE PROCESSOS
A2: 📊 RESUMO EXECUTIVO EM TEMPO REAL
A3: 📋 Total | B3: 🚀 Ativos | C3: ✅ Concluídos | D3: ⏸️ Planejados | E3: 🔴 Críticos | F3: 💯 Saúde Geral | G3: 💰 Orçamento Total | H3: 📈 Eficiência Média
A4: =COUNTA(A6:A100)-COUNTIF(A6:A100,"") -> -89 | B4: =COUNTIF(C6:C100,"Em execução") -> 0 | C4: =COUNTIF(C6:C100,"Concluída") -> 0 | D4: =COUNTIF(C6:C100,"Planejada") -> 0 | E4: =COUNTIF(L6:L100,"🔴 Alto") -> 0 | F4: =AVERAGE(G6:G100) -> 0 | G4: =SUM(N6:N100) -> 48000 | H4: =AVERAGE(O6:O100) -> #NAME?
A5: ID | B5: Processo | C5: Status | D5: Responsável Principal | E5: Data Início | F5: Data Término | G5: % Concluído | H5: Etapas Concluídas | I5: Tempo Est. | J5: Tempo Real | K5: Dias Rest. | L5: Risco | M5: Saúde | N5: Custo Est. | O5: Eficiência | P5: Link
A6: 1 | B6: Mapeamento Processos GGOV | C6: ='Processo 1'!I2 -> 0 | D6: ='Processo 1'!C15 -> #NAME? | E6: 46001 | F6: 46053 | G6: ='Processo 1'!K2 -> 0 | H6: ='Processo 1'!L2 -> 0 | I6: =F6-E6 -> 52 | J6: =HOJE()-E6 -> #NAME? | K6: =F6-HOJE() -> #NAME? | L6: =SE(K6<0,"🔴 Alto",SE(K6<3,"🟡 Médio","🟢 Baixo")) -> #NAME? | M6: =SE(G6>=0.8,"🟢 Excelente",SE(G6>=0.6,"🟡 Bom",SE(G6>=0.3,"🟠 Regular","🔴 Crítico"))) -> #NAME? | N6: 15000 | O6: ='Processo 1'!J4 -> #NAME? | P6: Processo 1
A7: 2 | B7: Atualização Normativas Internas | C7: ='Processo 2'!I2 -> 0 | D7: ='Processo 2'!C15 -> #NAME? | E7: 45996 | F7: 46011 | G7: ='Processo 2'!K2 -> 0 | H7: ='Processo 2'!L2 -> 0 | I7: =F7-E7 -> 15 | J7: =HOJE()-E7 -> #NAME? | K7: =F7-HOJE() -> #NAME? | L7: =SE(K7<0,"🔴 Alto",SE(K7<3,"🟡 Médio","🟢 Baixo")) -> #NAME? | M7: =SE(G7>=0.8,"🟢 Excelente",SE(G7>=0.6,"🟡 Bom",SE(G7>=0.3,"🟠 Regular","🔴 Crítico"))) -> #NAME? | N7: 8000 | O7: ='Processo 2'!J4 -> #NAME? | P7: Processo 2
A8: 3 | B8: Implantação Sistema GED | C8: ='Processo 3'!I2 -> 0 | D8: ='Processo 3'!C15 -> #NAME? | E8: 46006 | F8: 46068 | G8: ='Processo 3'!K2 -> 0 | H8: ='Processo 3'!L2 -> 0 | I8: =F8-E8 -> 62 | J8: =HOJE()-E8 -> #NAME? | K8: =F8-HOJE() -> #NAME? | L8: =SE(K8<0,"🔴 Alto",SE(K8<3,"🟡 Médio","🟢 Baixo")) -> #NAME? | M8: =SE(G8>=0.8,"🟢 Excelente",SE(G8>=0.6,"🟡 Bom",SE(G8>=0.3,"🟠 Regular","🔴 Crítico"))) -> #NAME? | N8: 25000 | O8: ='Processo 3'!J4 -> #NAME? | P8: Processo 3

Sheet Processo 1
A1: Projeto Mapeamento dos processos do GGOV | B1: Descrição da demanda | C1: Realizar o mapeamento completo dos processos administrativos e operacionais do Gabinete de Governança (GGOV), com a finalidade de otimizar o desempenho. | I1: Status Geral | J1: ⬅️ Voltar | K1: % Conclusão | L1: Etapas
A3: SEI: | B3: 0000000000000 | C3: Prioridade: | D3: Alta | E3: Categoria: | F3: Mapeamento | G3: Risco: | H3: =SE(K2<0.3,"🔴 Alto",SE(K2<0.7,"🟡 Médio","🟢 Baixo")) -> #NAME? | I3: Orçamento: | J3: 15000 | K3: Gasto Real: | L3: =SOMA(K8:K13) -> #NAME?
A4: Início: | B4: 46001 | C4: Término: | D4: 46053 | E4: Duração: | F4: =D4-B4 -> 52 | G4: Dias Rest.: | H4: =D4-HOJE() -> #NAME? | I4: Eficiência: | J4: =SE(J3=0,0,1-(L3/J3)) -> #NAME? | K4: Coord. Atual: | L4: =TEXTOJUNTAR(", ",VERDADEIRO,ÚNICO(FILTRAR(C8:C13,C8:C13<>""))) -> #NAME?
A7: Etapa | B7: Status | C7: Responsável | D7: Dt. Início | E7: Dt. Término | F7: Produtos/Entregas | G7: Dependência | H7: % Progresso | I7: Horas Est. | J7: Horas Real | K7: Custo | L7: Tarefas Detalhadas
A8: Levantamento | B8: Em execução | C8: Luma Damon | D8: 46001 | E8: 46038 | F8: Plano do projeto | G8: - | H8: 0.7 | I8: 80 | J8: 56 | K8: 2800 | L8: 1. Entrevistas 2. Coleta docs
A9: Mapeamento | B9: Em execução | C9: Suerlei Gondim | D9: 46001 | E9: 46053 | F9: Relatório | G9: Etapa 1 | H9: 0.6 | I9: 120 | J9: 72 | K9: 3600 | L9: 1. Documentar 2. Gargalos
A10: Análise | B10: Não iniciada | C10: Pedro Analista | D10: 46039 | E10: 46068 | F10: Mapas | G10: Etapa 1,2 | H10: 0 | I10: 100 | J10: 0 | K10: 0 | L10: 1. Eficiência 2. Melhorias
A11: Documentação | B11: Não iniciada | C11: Ana Documentadora | D11: 46054 | E11: 46081 | F11: Relatório Final | G11: Etapa 3 | H11: 0 | I11: 80 | J11: 0 | K11: 0 | L11: 1. Consolidar 2. Apresentar
A12: Validação | B12: Não iniciada | C12: Diretor GGOV | D12: 46073 | E12: 46091 | F12: Aprovação | G12: Etapa 4 | H12: 0 | I12: 40 | J12: 0 | K12: 0 | L12: 1. Revisar 2. Aprovar
A13: Implementação | B13: Não iniciada | C13: Equipe GGOV | D13: 46082 | E13: 46112 | F13: Processos Ativos | G13: Etapa 5 | H13: 0 | I13: 60 | J13: 0 | K13: 0 | L13: 1. Treinar 2. Monitorar
A15: Responsável Principal (Auto): | C15: =ÍNDICE(C8:C13,MODO(CORRESP(C8:C13,C8:C13,0),CORRESP(C8:C13,C8:C13,0))) -> #NAME?

Sheet Processo 2
A1: Projeto Atualização de Normativas Internas | B1: Descrição da demanda | C1: Revisar e atualizar todas as normativas internas do GGOV para garantir conformidade com as novas diretrizes e legislação vigente. | I1: Status Geral | J1: ⬅️ Voltar | K1: % Conclusão | L1: Etapas
A3: SEI: | B3: 0000000000000 | C3: Prioridade: | D3: Crítica | E3: Categoria: | F3: Normativas | G3: Risco: | H3: =SE(K2<0.3,"🔴 Alto",SE(K2<0.7,"🟡 Médio","🟢 Baixo")) -> #NAME? | I3: Orçamento: | J3: 8000 | K3: Gasto Real: | L3: =SOMA(K8:K13) -> #NAME?
A4: Início: | B4: 45996 | C4: Término: | D4: 46011 | E4: Duração: | F4: =D4-B4 -> 15 | G4: Dias Rest.: | H4: =D4-HOJE() -> #NAME? | I4: Eficiência: | J4: =SE(J3=0,0,1-(L3/J3)) -> #NAME? | K4: Coord. Atual: | L4: =TEXTOJUNTAR(", ",VERDADEIRO,ÚNICO(FILTRAR(C8:C13,C8:C13<>""))) -> #NAME?
A7: Etapa | B7: Status | C7: Responsável | D7: Dt. Início | E7: Dt. Término | F7: Produtos/Entregas | G7: Dependência | H7: % Progresso | I7: Horas Est. | J7: Horas Real | K7: Custo | L7: Tarefas Detalhadas
A8: Revisão Legislação | B8: Em execução | C8: Maria Santos | D8: 45996 | E8: 46003 | F8: Checklist Legal | G8: - | H8: 0.8 | I8: 40 | J8: 32 | K8: 1600 | L8: 1. Leis 2. Decretos
A9: Análise Impacto | B9: Em execução | C9: João Jurídico | D9: 45999 | E9: 46006 | F9: Relatório Impacto | G9: Etapa 1 | H9: 0.6 | I9: 30 | J9: 18 | K9: 900 | L9: 1. Mudanças 2. Riscos
A10: Redação Normativas | B10: Não iniciada | C10: Equipe Jurídica | D10: 46004 | E10: 46009 | F10: Minutas | G10: Etapa 2 | H10: 0 | I10: 50 | J10: 0 | K10: 0 | L10: 1. Redigir 2. Revisar
A11: Validação Interna | B11: Não iniciada | C11: Comitê GGOV | D11: 46007 | E11: 46010 | F11: Aprovação | G11: Etapa 3 | H11: 0 | I11: 20 | J11: 0 | K11: 0 | L11: 1. Apresentar 2. Ajustar
A12: Publicação | B12: Não iniciada | C12: Comunicação | D12: 46010 | E12: 46011 | F12: Normativas Publicadas | G12: Etapa 4 | H12: 0 | I12: 10 | J12: 0 | K12: 0 | L12: 1. Diagramar 2. Publicar
A13: Treinamento | B13: Não iniciada | C13: RH | D13: 46011 | E13: 46011 | F13: Equipe Capacitada | G13: Etapa 5 | H13: 0 | I13: 15 | J13: 0 | K13: 0 | L13: 1. Workshop 2. Material
A15: Responsável Principal (Auto): | C15: =ÍNDICE(C8:C13,MODO(CORRESP(C8:C13,C8:C13,0),CORRESP(C8:C13,C8:C13,0))) -> #NAME?

Sheet Processo 3
A1: Projeto Implantação do Sistema GED | B1: Descrição da demanda | C1: Implementar sistema de Gestão Eletrônica de Documentos para digitalização e controle de todos os documentos do gabinete. | I1: Status Geral | J1: ⬅️ Voltar | K1: % Conclusão | L1: Etapas
A3: SEI: | B3: 0000000000000 | C3: Prioridade: | D3: Média | E3: Categoria: | F3: TI/Sistemas | G3: Risco: | H3: =SE(K2<0.3,"🔴 Alto",SE(K2<0.7,"🟡 Médio","🟢 Baixo")) -> #NAME? | I3: Orçamento: | J3: 25000 | K3: Gasto Real: | L3: =SOMA(K8:K13) -> #NAME?
A4: Início: | B4: 46006 | C4: Término: | D4: 46068 | E4: Duração: | F4: =D4-B4 -> 62 | G4: Dias Rest.: | H4: =D4-HOJE() -> #NAME? | I4: Eficiência: | J4: =SE(J3=0,0,1-(L3/J3)) -> #NAME? | K4: Coord. Atual: | L4: =TEXTOJUNTAR(", ",VERDADEIRO,ÚNICO(FILTRAR(C8:C13,C8:C13<>""))) -> #NAME?
A7: Etapa | B7: Status | C7: Responsável | D7: Dt. Início | E7: Dt. Término | F7: Produtos/Entregas | G7: Dependência | H7: % Progresso | I7: Horas Est. | J7: Horas Real | K7: Custo | L7: Tarefas Detalhadas
A8: Levantamento Requisitos | B8: Planejada | C8: Carlos Pereira | D8: 46006 | E8: 46019 | F8: Especificações | G8: - | H8: 0.2 | I8: 60 | J8: 12 | K8: 600 | L8: 1. Reuniões 2. Documentar
A9: Seleção Fornecedor | B9: Não iniciada | C9: Compras | D9: 46011 | E9: 46032 | F9: Contrato | G9: Etapa 1 | H9: 0 | I9: 40 | J9: 0 | K9: 0 | L9: 1. Pesquisa 2. Cotação
A10: Customização Sistema | B10: Não iniciada | C10: Equipe TI | D10: 46033 | E10: 46053 | F10: Sistema Config | G10: Etapa 2 | H10: 0 | I10: 120 | J10: 0 | K10: 0 | L10: 1. Parametrizar 2. Integrar
A11: Migração Dados | B11: Não iniciada | C11: DBA | D11: 46047 | E11: 46058 | F11: Base Migrada | G11: Etapa 3 | H11: 0 | I11: 80 | J11: 0 | K11: 0 | L11: 1. Extrair 2. Importar
A12: Testes | B12: Não iniciada | C12: QA Team | D12: 46054 | E12: 46063 | F12: Homologação | G12: Etapa 4 | H12: 0 | I12: 50 | J12: 0 | K12: 0 | L12: 1. Testar 2. Ajustar
A13: Go-Live | B13: Não iniciada | C13: TI + GGOV | D13: 46064 | E13: 46068 | F13: Sistema Prod | G13: Etapa 5 | H13: 0 | I13: 30 | J13: 0 | K13: 0 | L13: 1. Deploy 2. Suporte
A15: Responsável Principal (Auto): | C15: =ÍNDICE(C8:C13,MODO(CORRESP(C8:C13,C8:C13,0),CORRESP(C8:C13,C8:C13,0))) -> #NAME?

Sheet Dashboard
A1: 📊 DASHBOARD EXECUTIVO - VISÃO ESTRATÉGICA 360°
A3: 📅 Atualizado automaticamente em: 10/12/2025 21:45
A5: 🎯 INDICADORES ESTRATÉGICOS EM TEMPO REAL
A6: 📋 Total | B6: 🚀 Ativos | C6: ✅ Concluídos | D6: ⚠️ Críticos | E6: 📈 Taxa Sucesso | F6: 💯 Saúde | G6: 💰 Orçamento | H6: ⚡ Eficiência
A7: =CONT.VALORES('Página inicial'!A6:A100) -> #NAME? | B7: =CONT.SE('Página inicial'!C:C,"Em execução") -> #NAME? | C7: =CONT.SE('Página inicial'!C:C,"Concluída") -> #NAME? | D7: =CONT.SE('Página inicial'!L:L,"*Alto*") -> #NAME? | E7: =TEXTO(D6/B6,"0%") -> #NAME? | F7: =MÉDIA('Página inicial'!G6:G20) -> #NAME? | G7: =SOMA('Página inicial'!N6:N20) -> #NAME? | H7: =MÉDIA('Página inicial'!O6:O20) -> #NAME?
A10: Status | B10: Quantidade
A11: Em execução | B11: =CONT.SE('Página inicial'!C:C,"Em execução") -> #NAME?
A12: Concluída | B12: =CONT.SE('Página inicial'!C:C,"Concluída") -> #NAME?
A13: Planejada | B13: =CONT.SE('Página inicial'!C:C,"Planejada") -> #NAME?
A14: Bloqueada | B14: =CONT.SE('Página inicial'!C:C,"Bloqueada") -> #NAME?

Sheet Instruções
A1: 📖 GUIA DO SISTEMA MELHORADO
A3: 🚀 SISTEMA PRO MELHORADO - AUTOMAÇÕES COMPLETAS
A5: ✨ NOVIDADES DESTA VERSÃO:
A7: 📊 PÁGINA INICIAL APRIMORADA:
A8: • KPIs em tempo real no topo da página
A9: • Coluna 'Etapas Concluídas' mostra progresso visual
A10: • Responsável Principal sincronizado automaticamente
A11: • % Conclusão calculado pela média das etapas
A12: • Indicadores de Saúde em 4 níveis (Excelente/Bom/Regular/Crítico)
A13: • Data Bars visuais para % de progresso
A14: • Ícones de status para etapas concluídas
A16: 🤖 AUTOMAÇÕES NOS PROCESSOS:
... A40: 💡 Tudo está conectado e sincronizado automaticamente!
